odoo/addons/odoo_2_odoo_data_transfer/README.rst
odoo/addons/odoo_2_odoo_data_transfer/__init__.py
odoo/addons/odoo_2_odoo_data_transfer/__manifest__.py
odoo/addons/odoo_2_odoo_data_transfer/data/ir_exports.xml
odoo/addons/odoo_2_odoo_data_transfer/demo/odoo.data.transfer.template.csv
odoo/addons/odoo_2_odoo_data_transfer/demo/odoo.data.transfer.template.line.csv
odoo/addons/odoo_2_odoo_data_transfer/i18n/es.po
odoo/addons/odoo_2_odoo_data_transfer/models/__init__.py
odoo/addons/odoo_2_odoo_data_transfer/models/ir_model.py
odoo/addons/odoo_2_odoo_data_transfer/models/ir_model_fields.py
odoo/addons/odoo_2_odoo_data_transfer/models/odoo_data_transfer_log.py
odoo/addons/odoo_2_odoo_data_transfer/models/odoo_data_transfer_log_field.py
odoo/addons/odoo_2_odoo_data_transfer/models/odoo_data_transfer_log_record.py
odoo/addons/odoo_2_odoo_data_transfer/models/odoo_data_transfer_template.py
odoo/addons/odoo_2_odoo_data_transfer/models/odoo_data_transfer_template_line.py
odoo/addons/odoo_2_odoo_data_transfer/models/odoo_data_transfer_template_line_mixin.py
odoo/addons/odoo_2_odoo_data_transfer/models/odoo_data_transfer_template_mixin.py
odoo/addons/odoo_2_odoo_data_transfer/readme/CONTRIBUTORS.md
odoo/addons/odoo_2_odoo_data_transfer/readme/DESCRIPTION.md
odoo/addons/odoo_2_odoo_data_transfer/readme/ROADMAP.md
odoo/addons/odoo_2_odoo_data_transfer/readme/USAGE.md
odoo/addons/odoo_2_odoo_data_transfer/security/ir.model.access.csv
odoo/addons/odoo_2_odoo_data_transfer/static/description/icon.png
odoo/addons/odoo_2_odoo_data_transfer/static/description/index.html
odoo/addons/odoo_2_odoo_data_transfer/templates/product_template.xlsx
odoo/addons/odoo_2_odoo_data_transfer/templates/res_partner.xlsx
odoo/addons/odoo_2_odoo_data_transfer/templates/sale_order.csv
odoo/addons/odoo_2_odoo_data_transfer/tests/__init__.py
odoo/addons/odoo_2_odoo_data_transfer/tests/test_odoo_2_odoo_data_transfer.py
odoo/addons/odoo_2_odoo_data_transfer/views/menuitems.xml
odoo_addon_odoo_2_odoo_data_transfer-17.0.1.3.0.dist-info/METADATA
odoo_addon_odoo_2_odoo_data_transfer-17.0.1.3.0.dist-info/WHEEL
odoo_addon_odoo_2_odoo_data_transfer-17.0.1.3.0.dist-info/top_level.txt
odoo_addon_odoo_2_odoo_data_transfer-17.0.1.3.0.dist-info/RECORD
