Metadata-Version: 2.1
Name: odoo-addon-odoo_2_odoo_data_transfer
Version: 17.0.1.3.0
Requires-Python: >=3.10
Requires-Dist: odoo>=17.0a,<17.1dev
Summary: Generic tools to manage data transfer between Odoos
Home-page: https://github.com/sygel-technology/sy-server-backend
License: AGPL-3
Author: Sygel, Odoo Community Association (OCA)
Author-email: support@odoo-community.org
Classifier: Programming Language :: Python
Classifier: Framework :: Odoo
Classifier: Framework :: Odoo :: 17.0
Classifier: License :: OSI Approved :: GNU Affero General Public License v3
